LICENSE.txt
README.md
setup.py
wolf_smart/__init__.py
wolf_smart/constants.py
wolf_smart/create_session.py
wolf_smart/helpers.py
wolf_smart/models.py
wolf_smart/token_auth.py
wolf_smart/wolf_client.py
wolf_smart.egg-info/PKG-INFO
wolf_smart.egg-info/SOURCES.txt
wolf_smart.egg-info/dependency_links.txt
wolf_smart.egg-info/requires.txt
wolf_smart.egg-info/top_level.txt