Metadata-Version: 2.1
Name: wolf-smart
Version: 0.0.7
Summary: A package to communicate with Wolf SmartSet Cloud
Home-page: https://github.com/mtielen/wolf-smart
Author: Jan Rothkegel
Author-email: jan.rothkegel@web.de
License: UNKNOWN
Platform: UNKNOWN
Classifier: Programming Language :: Python :: 3
Classifier: Operating System :: OS Independent
License-File: LICENSE.txt
